rust_circuit-0.4.12.dist-info/METADATA
rust_circuit-0.4.12.dist-info/WHEEL
rust_circuit/__init__.py
rust_circuit/_rust.py
rust_circuit/_rust.pyi
rust_circuit/algebric_rewrite.py
rust_circuit/causal_scrubbing/__init__.py
rust_circuit/causal_scrubbing/dataset.py
rust_circuit/causal_scrubbing/experiment.py
rust_circuit/causal_scrubbing/hypothesis.py
rust_circuit/causal_scrubbing/testing_utils.py
rust_circuit/cum_algo.py
rust_circuit/demos/__init__.py
rust_circuit/demos/causal_scrubbing/__init__.py
rust_circuit/demos/causal_scrubbing/causal_scrubbing_simple.py
rust_circuit/demos/causal_scrubbing/incr_number_simple.py
rust_circuit/demos/causal_scrubbing/pool.py
rust_circuit/demos/notebook_testing.py
rust_circuit/demos/paren_balancer/__init__.py
rust_circuit/demos/paren_balancer/causal_scrubbing_experiments.py
rust_circuit/demos/paren_balancer/setup.py
rust_circuit/demos/paren_balancer/test_paren_balancer_exercises.py
rust_circuit/demos/paren_balancer/writeup_attribution_plots.py
rust_circuit/demos/rust_circuit_demos/__init__.py
rust_circuit/demos/rust_circuit_demos/basic_scope_manager.py
rust_circuit/demos/rust_circuit_demos/custom_general_function.py
rust_circuit/demos/rust_circuit_demos/fancy_error.py
rust_circuit/demos/rust_circuit_demos/handcrafted_model_cumulants.py
rust_circuit/demos/rust_circuit_demos/iterative_matchers.py
rust_circuit/demos/rust_circuit_demos/modules_and_symbols.py
rust_circuit/demos/rust_circuit_demos/nest.py
rust_circuit/demos/rust_circuit_demos/printing_parsing.py
rust_circuit/demos/rust_circuit_demos/push_down_index.py
rust_circuit/demos/rust_circuit_demos/push_down_module.py
rust_circuit/demos/rust_circuit_demos/save_models.py
rust_circuit/demos/rust_circuit_demos/simp.py
rust_circuit/demos/rust_circuit_demos/transformer_config.py
rust_circuit/demos/rust_circuit_demos/uitest.py
rust_circuit/general_function_spec_base.py
rust_circuit/generalfuncs/mlp_topk.py
rust_circuit/generalfuncs/rotary_pos_emb.py
rust_circuit/generalfuncs/test_a_samp_multinomial.py
rust_circuit/generalfuncs/train_mask.py
rust_circuit-0.4.12.dist-info/RECORD
