Metadata-Version: 2.1
Name: rust_circuit
Version: 0.4.12
Requires-Dist: torch
Requires-Dist: attrs
Requires-Dist: cattrs
Requires-Dist: blake3
Requires-Dist: numpy
Requires-Dist: msgpack
Requires-Dist: typing_extensions
